tosholi/__init__.py
tosholi/format.py
tosholi/parse.py
tosholi/protocols.py
tosholi/py.typed
tosholi/validate.py
tosholi-0.1.0.dist-info/LICENSE
tosholi-0.1.0.dist-info/METADATA
tosholi-0.1.0.dist-info/WHEEL
tosholi-0.1.0.dist-info/top_level.txt
tosholi-0.1.0.dist-info/RECORD
